robotframework_scaffold/cli.py
robotframework_scaffold/scaffolder/__init__.py
robotframework_scaffold/scaffolder/base_resource.py
robotframework_scaffold/scaffolder/constants.py
robotframework_scaffold/scaffolder/creator.py
robotframework_scaffold/scaffolder/poetry_setup.py
robotframework_scaffold/scaffolder/preview.py
robotframework_scaffold/scaffolder/prompts.py
robotframework_scaffold/scaffolder/readme.py
robotframework_scaffold/scaffolder/structure.py
robotframework_scaffold/scaffolder/suite_generator.py
robotframework_scaffold/scaffolder/templates/api/create_contracts_routes/contracts_generator.py
robotframework_scaffold/scaffolder/templates/api/create_session/session_generator.py
robotframework_scaffold/scaffolder/venv_setup.py
robotframework_scaffold-1.0.2.dist-info/LICENSE
robotframework_scaffold-1.0.2.dist-info/METADATA
robotframework_scaffold-1.0.2.dist-info/WHEEL
robotframework_scaffold-1.0.2.dist-info/entry_points.txt
robotframework_scaffold-1.0.2.dist-info/RECORD
