Metadata-Version: 2.1
Name: robotframework-scaffold
Version: 1.0.2
Summary: A scaffold tool for structuring Robot Framework projects with best practices.
License: MIT
Author: Robot Courses
Author-email: git@robotcourses.com.br
Requires-Python: >=3.8,<4.0
Classifier: License :: OSI Approved :: MIT License
Classifier: Programming Language :: Python :: 3
Classifier: Programming Language :: Python :: 3.8
Classifier: Programming Language :: Python :: 3.9
Classifier: Programming Language :: Python :: 3.10
Classifier: Programming Language :: Python :: 3.11
Classifier: Programming Language :: Python :: 3.12
Classifier: Programming Language :: Python :: 3.13
Requires-Dist: click (==8.1.8)
Requires-Dist: pyyaml (>=6.0.2,<7.0.0)
